promptx/__init__.py
promptx/promptx.py
promptx-0.0.7.dist-info/LICENSE.md
promptx-0.0.7.dist-info/METADATA
promptx-0.0.7.dist-info/WHEEL
promptx-0.0.7.dist-info/top_level.txt
promptx-0.0.7.dist-info/RECORD
