Metadata-Version: 2.1
Name: promptx
Version: 0.0.7
Summary: Flexible prompt wrapper for dmenu, fzf, and rofi.
License: GNU General Public License v3 (GPLv3)
Project-URL: repository, https://codeberg.org/johndovern/promptx
Keywords: dmenu,fzf,rofi
License-File: LICENSE.md
